Metadata-Version: 2.1
Name: fast_text_detection
Version: 0.0.1
Summary: Python text detection package
Home-page: https://github.com/gnana70/
Author: Gnana Prasath
Author-email: Gnana Prasath <gnana70@gmail.com>
License: MIT License
Project-URL: Homepage, https://github.com/gnana70/
Keywords: text detection,ocr,Scene text detection
Classifier: License :: OSI Approved :: MIT License
Classifier: Programming Language :: Python
Classifier: Programming Language :: Python :: 3
Requires-Python: >=3.9
License-File: LICENSE
Requires-Dist: torch
Requires-Dist: torchvision
Requires-Dist: Pillow
Requires-Dist: opencv-python
Requires-Dist: shapely
Requires-Dist: tqdm
Requires-Dist: numpy
Requires-Dist: pyclipper
Requires-Dist: anyascii
Requires-Dist: scipy
Provides-Extra: dev
Requires-Dist: black ; extra == 'dev'
Requires-Dist: bumpver ; extra == 'dev'
Requires-Dist: isort ; extra == 'dev'
Requires-Dist: pip-tools ; extra == 'dev'
Requires-Dist: pytest ; extra == 'dev'
